PogoOCR/__init__.py
PogoOCR/cloudvision.py
PogoOCR/exceptions.py
PogoOCR/numbers.py
PogoOCR/pattern_lookups.json
PogoOCR/types.py
PogoOCR-0.3.9.data/data/PogoOCR/pattern_lookups.json
PogoOCR-0.3.9.dist-info/LICENSE
PogoOCR-0.3.9.dist-info/METADATA
PogoOCR-0.3.9.dist-info/WHEEL
PogoOCR-0.3.9.dist-info/top_level.txt
PogoOCR-0.3.9.dist-info/RECORD
